space_packet_parser/__init__.py
space_packet_parser/cli.py
space_packet_parser/common.py
space_packet_parser/definitions.py
space_packet_parser/exceptions.py
space_packet_parser/packets.py
space_packet_parser/xarr.py
space_packet_parser/generators/__init__.py
space_packet_parser/generators/ccsds.py
space_packet_parser/generators/fixed_length.py
space_packet_parser/generators/udp.py
space_packet_parser/generators/utils.py
space_packet_parser/xtce/__init__.py
space_packet_parser/xtce/calibrators.py
space_packet_parser/xtce/comparisons.py
space_packet_parser/xtce/containers.py
space_packet_parser/xtce/definitions.py
space_packet_parser/xtce/encodings.py
space_packet_parser/xtce/parameter_types.py
space_packet_parser/xtce/parameters.py
space_packet_parser/xtce/validation.py
space_packet_parser-6.1.0.dist-info/METADATA
space_packet_parser-6.1.0.dist-info/WHEEL
space_packet_parser-6.1.0.dist-info/entry_points.txt
space_packet_parser-6.1.0.dist-info/licenses/LICENSE.txt
space_packet_parser-6.1.0.dist-info/RECORD
