Metadata-Version: 2.4
Name: space_packet_parser
Version: 6.1.0
Summary: A CCSDS telemetry packet decoding library based on the XTCE packet format description standard.
Project-URL: repository, https://github.com/lasp/space_packet_parser
Project-URL: homepage, https://github.com/lasp/space_packet_parser
Project-URL: documentation, https://space-packet-parser.readthedocs.io
Author-email: Gavin Medley <gavin.medley@lasp.colorado.edu>, Greg Lucas <greg.lucas@lasp.colorado.edu>, Michael Chambliss <michael.chambliss@lasp.colorado.edu>
Maintainer-email: Gavin Medley <gavin.medley@lasp.colorado.edu>, Greg Lucas <greg.lucas@lasp.colorado.edu>
License: BSD-3-Clause
License-File: LICENSE.txt
Keywords: binary data,ccsds,data decoding,data encoding,data extraction,data manipulation,data processing,data transformation,lasp,packet inspection,packet parsing,python,space data systems,space packet protocol,university of colorado,xtce
Classifier: Development Status :: 5 - Production/Stable
Classifier: Intended Audience :: Developers
Classifier: Intended Audience :: Science/Research
Classifier: License :: OSI Approved :: BSD License
Classifier: Operating System :: OS Independent
Classifier: Programming Language :: Python :: 3
Classifier: Topic :: Scientific/Engineering
Classifier: Topic :: Software Development :: Libraries :: Python Modules
Requires-Python: >=3.10
Requires-Dist: click>=8.0
Requires-Dist: lxml>=4.8.0
Requires-Dist: rich>=13.0
Provides-Extra: docs
Requires-Dist: myst-parser; extra == 'docs'
Requires-Dist: pyyaml; extra == 'docs'
Requires-Dist: sphinx; extra == 'docs'
Requires-Dist: sphinx-autoapi; extra == 'docs'
Requires-Dist: sphinx-rtd-theme; extra == 'docs'
Provides-Extra: examples
Requires-Dist: matplotlib>=3.4; extra == 'examples'
Requires-Dist: xarray>2024.0.0; extra == 'examples'
Provides-Extra: test
Requires-Dist: numpy; extra == 'test'
Requires-Dist: pre-commit; extra == 'test'
Requires-Dist: pytest; extra == 'test'
Requires-Dist: pytest-benchmark; extra == 'test'
Requires-Dist: pytest-cov; extra == 'test'
Requires-Dist: pytest-randomly; extra == 'test'
Requires-Dist: pyyaml; extra == 'test'
Requires-Dist: ruff; extra == 'test'
Requires-Dist: tomli; extra == 'test'
Requires-Dist: xarray; extra == 'test'
Provides-Extra: xarray
Requires-Dist: numpy>=1.26.0; extra == 'xarray'
Requires-Dist: xarray>2024.0.0; extra == 'xarray'
